morepython/__init__.py
morepython/dict_utils.py
morepython/iter_utils.py
morepython/metadata.py
morepython/os_utils.py
morepython/regex_utils.py
morepython/time_utils.py
morepython-0.0.2.dist-info/METADATA
morepython-0.0.2.dist-info/WHEEL
morepython-0.0.2.dist-info/top_level.txt
morepython-0.0.2.dist-info/RECORD
